nav2d/__init__.py
nav2d/assets/__init__.py
nav2d/assets/elements.py
nav2d/assets/regions.py
nav2d/envs/__init__.py
nav2d/envs/base.py
nav2d/envs/envs.py
nav2d-0.0.2.dist-info/LICENSE
nav2d-0.0.2.dist-info/METADATA
nav2d-0.0.2.dist-info/WHEEL
nav2d-0.0.2.dist-info/top_level.txt
nav2d-0.0.2.dist-info/RECORD
