Metadata-Version: 2.1
Name: nav2d
Version: 0.0.2
Summary: 2D Navigation Gym Environment
Home-page: https://github.com/xxArbiter/nav2d
Download-URL: https://github.com/xxArbiter/nav2d/archive/refs/tags/0.0.2.tar.gz
Author: Xiaoyu Wang
Author-email: Xiaoyu Wang <cnxiaoyu.wang@mail.utoronto.ca>, Jihwan Jeong <jiihwan.jeong@gmail.com>
License: MIT License
Project-URL: Homepage, https://github.com/xxArbiter/nav2d
Project-URL: Bug Tracker, https://github.com/xxArbiter/nav2d/issues
Keywords: gym,navigation,rl
Classifier: Programming Language :: Python :: 3
Classifier: License :: OSI Approved :: MIT License
Classifier: Operating System :: OS Independent
Requires-Python: >=3.8
License-File: LICENSE
Requires-Dist: numpy
Requires-Dist: pygame
Requires-Dist: gym
